pitch/__init__.py
pitch-0.0.6.dist-info/LICENSE
pitch-0.0.6.dist-info/METADATA
pitch-0.0.6.dist-info/WHEEL
pitch-0.0.6.dist-info/top_level.txt
pitch-0.0.6.dist-info/RECORD
