Metadata-Version: 2.1
Name: pitch
Version: 0.0.6
Summary: To find pitch of an audio file
Home-page: https://github.com/ParthMehta15/Pitch
Author: Sunil Karamchandani,
License: UNKNOWN
Platform: UNKNOWN
Classifier: Programming Language :: Python :: 3
Classifier: License :: OSI Approved :: MIT License
Classifier: Operating System :: OS Independent
